scrapy_official_newspapers/__init__.py
scrapy_official_newspapers/functions.py
scrapy_official_newspapers/items.py
scrapy_official_newspapers/middlewares.py
scrapy_official_newspapers/models.py
scrapy_official_newspapers/pipelines.py
scrapy_official_newspapers/spiders/__init__.py
scrapy_official_newspapers/spiders/elperuano.py
scrapy_official_newspapers/spiders/leychile_spider.py
scrapy_official_newspapers/spiders/mexicoDOF.py
scrapy_omdena_latam-0.0.2.dist-info/LICENSE
scrapy_omdena_latam-0.0.2.dist-info/METADATA
scrapy_omdena_latam-0.0.2.dist-info/WHEEL
scrapy_omdena_latam-0.0.2.dist-info/top_level.txt
scrapy_omdena_latam-0.0.2.dist-info/RECORD
