Metadata-Version: 2.1
Name: scrapy-omdena-latam
Version: 0.0.2
Summary: Web Crawling application running Scrapy Tool extracting official policies
Home-page: https://github.com/frapercan/scrapy_omdena_latam
Author: Martin Hadid
Author-email: martinhadid@gmail.com
License: MIT
Download-URL: https://pypi.org/project/scrapy_omdena_latam/
Keywords: scrapy,scraper,omdena
Platform: UNKNOWN
Requires-Dist: attrs (==20.2.0)
Requires-Dist: Automat (==20.2.0)
Requires-Dist: boto3 (==1.15.16)
Requires-Dist: botocore (==1.18.16)
Requires-Dist: cffi (==1.14.3)
Requires-Dist: constantly (==15.1.0)
Requires-Dist: cryptography (==3.1.1)
Requires-Dist: cssselect (==1.1.0)
Requires-Dist: dateparser (==0.7.6)
Requires-Dist: hyperlink (==20.0.1)
Requires-Dist: idna (==2.10)
Requires-Dist: incremental (==17.5.0)
Requires-Dist: itemadapter (==0.1.1)
Requires-Dist: itemloaders (==1.0.3)
Requires-Dist: jmespath (==0.10.0)
Requires-Dist: lxml (==4.5.2)
Requires-Dist: numpy (==1.19.2)
Requires-Dist: pandas (==1.1.3)
Requires-Dist: parsel (==1.6.0)
Requires-Dist: pkg-resources (==0.0.0)
Requires-Dist: Protego (==0.1.16)
Requires-Dist: pyasn1 (==0.4.8)
Requires-Dist: pyasn1-modules (==0.2.8)
Requires-Dist: pycparser (==2.20)
Requires-Dist: PyDispatcher (==2.0.5)
Requires-Dist: PyHamcrest (==2.0.2)
Requires-Dist: PyMySQL (==0.10.1)
Requires-Dist: pyOpenSSL (==19.1.0)
Requires-Dist: python-dateutil (==2.8.1)
Requires-Dist: pytz (==2020.1)
Requires-Dist: queuelib (==1.5.0)
Requires-Dist: regex (==2020.10.11)
Requires-Dist: s3transfer (==0.3.3)
Requires-Dist: Scrapy (==2.4.0)
Requires-Dist: service-identity (==18.1.0)
Requires-Dist: six (==1.15.0)
Requires-Dist: SQLAlchemy (==1.3.19)
Requires-Dist: Twisted (==20.3.0)
Requires-Dist: tzlocal (==2.1)
Requires-Dist: urllib3 (==1.25.10)
Requires-Dist: w3lib (==1.22.0)
Requires-Dist: zope.interface (==5.1.2)
